extra_field/__init__.py
extra_field/admin.py
extra_field/apps.py
extra_field/models.py
extra_field/migrations/0001_initial.py
extra_field/migrations/__init__.py
django_extra_model_fields-1.0.dist-info/LICENSE
django_extra_model_fields-1.0.dist-info/METADATA
django_extra_model_fields-1.0.dist-info/WHEEL
django_extra_model_fields-1.0.dist-info/top_level.txt
django_extra_model_fields-1.0.dist-info/RECORD
