Metadata-Version: 2.1
Name: django-extra-model-fields
Version: 1.0
Summary: A Django app for adding and managing extra fields on any model.
Home-page: https://github.com/omerbhatti/django-extra-fields
Author: Omer Bhatti
Author-email: omerbhatti340@gmail.com
License: MIT
Classifier: Environment :: Web Environment
Classifier: Framework :: Django
Classifier: Framework :: Django :: 3.2
Classifier: License :: OSI Approved :: MIT License
Classifier: Operating System :: OS Independent
Classifier: Programming Language :: Python
Classifier: Programming Language :: Python :: 3
License-File: LICENSE
Requires-Dist: django >=3.2
